{
	"$schema": "http://schema.management.azure.com/schemas/2015-01-01/deploymentTemplate.json#",
	"contentVersion": "1.0.0.0",
	"parameters": {
		"factoryName": {
			"type": "string",
			"metadata": "Data Factory name",
			"defaultValue": "demodatafactoryabhi"
		},
		"AzureBlobStorage1_connectionString": {
			"type": "secureString",
			"metadata": "Secure string for 'connectionString' of 'AzureBlobStorage1'"
		},
		"LinkedServiceAzureSQLDatabase_password": {
			"type": "secureString",
			"metadata": "Secure string for 'password' of 'LinkedServiceAzureSQLDatabase'"
		},
		"linkedServiceSelfhost_password": {
			"type": "secureString",
			"metadata": "Secure string for 'password' of 'linkedServiceSelfhost'"
		},
		"LinkedServiceAzureSQLDatabase_properties_typeProperties_server": {
			"type": "string",
			"defaultValue": "mssqlserverabhi.database.windows.net"
		},
		"LinkedServiceAzureSQLDatabase_properties_typeProperties_database": {
			"type": "string",
			"defaultValue": "mssqldatabase"
		},
		"LinkedServiceAzureSQLDatabase_properties_typeProperties_userName": {
			"type": "string",
			"defaultValue": "abhi"
		},
		"linkedServiceSelfhost_properties_typeProperties_host": {
			"type": "string",
			"defaultValue": "\\\\LAPTOP-F9G5N51M\\Shared_folder"
		},
		"linkedServiceSelfhost_properties_typeProperties_userId": {
			"type": "string",
			"defaultValue": "laptop-f9g5n51m\\abhi"
		}
	},
	"variables": {
		"factoryId": "[concat('Microsoft.DataFactory/factories/', parameters('factoryName'))]"
	},
	"resources": [
		{
			"name": "[concat(parameters('factoryName'), '/CopyFilesToSQL')]",
			"type": "Microsoft.DataFactory/factories/pipelines",
			"apiVersion": "2018-06-01",
			"properties": {
				"activities": [
					{
						"name": "CopyFile1toSQL",
						"type": "Copy",
						"dependsOn": [
							{
								"activity": "Lookup1",
								"dependencyConditions": [
									"Succeeded"
								]
							}
						],
						"policy": {
							"timeout": "0.12:00:00",
							"retry": 0,
							"retryIntervalInSeconds": 30,
							"secureOutput": false,
							"secureInput": false
						},
						"userProperties": [],
						"typeProperties": {
							"source": {
								"type": "DelimitedTextSource",
								"storeSettings": {
									"type": "AzureBlobStorageReadSettings",
									"recursive": true,
									"enablePartitionDiscovery": false
								},
								"formatSettings": {
									"type": "DelimitedTextReadSettings"
								}
							},
							"sink": {
								"type": "AzureSqlSink",
								"writeBehavior": "insert",
								"sqlWriterUseTableLock": false,
								"disableMetricsCollection": false
							},
							"enableStaging": false,
							"translator": {
								"type": "TabularTranslator",
								"mappings": [
									{
										"source": {
											"name": "Id",
											"type": "String",
											"physicalType": "String"
										},
										"sink": {
											"name": "Id",
											"type": "Int32",
											"physicalType": "int"
										}
									},
									{
										"source": {
											"name": "Name",
											"type": "String",
											"physicalType": "String"
										},
										"sink": {
											"name": "Name",
											"type": "String",
											"physicalType": "varchar"
										}
									},
									{
										"source": {
											"name": "City",
											"type": "String",
											"physicalType": "String"
										},
										"sink": {
											"name": "City",
											"type": "String",
											"physicalType": "varchar"
										}
									}
								],
								"typeConversion": true,
								"typeConversionSettings": {
									"allowDataTruncation": true,
									"treatBooleanAsNumber": false
								}
							}
						},
						"inputs": [
							{
								"referenceName": "DelimitedText1",
								"type": "DatasetReference",
								"parameters": {}
							}
						],
						"outputs": [
							{
								"referenceName": "AzureSqlTable1",
								"type": "DatasetReference",
								"parameters": {}
							}
						]
					},
					{
						"name": "CopyFile2toSQL",
						"type": "Copy",
						"dependsOn": [
							{
								"activity": "CopyFile1toSQL",
								"dependencyConditions": [
									"Succeeded"
								]
							}
						],
						"policy": {
							"timeout": "0.12:00:00",
							"retry": 0,
							"retryIntervalInSeconds": 30,
							"secureOutput": false,
							"secureInput": false
						},
						"userProperties": [],
						"typeProperties": {
							"source": {
								"type": "DelimitedTextSource",
								"storeSettings": {
									"type": "AzureBlobStorageReadSettings",
									"recursive": true,
									"enablePartitionDiscovery": false
								},
								"formatSettings": {
									"type": "DelimitedTextReadSettings"
								}
							},
							"sink": {
								"type": "AzureSqlSink",
								"writeBehavior": "insert",
								"sqlWriterUseTableLock": false
							},
							"enableStaging": false,
							"translator": {
								"type": "TabularTranslator",
								"mappings": [
									{
										"source": {
											"name": "Id",
											"type": "String",
											"physicalType": "String"
										},
										"sink": {
											"name": "Id",
											"type": "Int32",
											"physicalType": "int"
										}
									},
									{
										"source": {
											"name": "Name",
											"type": "String",
											"physicalType": "String"
										},
										"sink": {
											"name": "Name",
											"type": "String",
											"physicalType": "varchar"
										}
									},
									{
										"source": {
											"name": "City",
											"type": "String",
											"physicalType": "String"
										},
										"sink": {
											"name": "City",
											"type": "String",
											"physicalType": "varchar"
										}
									}
								],
								"typeConversion": true,
								"typeConversionSettings": {
									"allowDataTruncation": true,
									"treatBooleanAsNumber": false
								}
							}
						},
						"inputs": [
							{
								"referenceName": "DelimitedText2",
								"type": "DatasetReference",
								"parameters": {}
							}
						],
						"outputs": [
							{
								"referenceName": "AzureSqlTable1",
								"type": "DatasetReference",
								"parameters": {}
							}
						]
					},
					{
						"name": "CopyFile3toSQL",
						"type": "Copy",
						"dependsOn": [
							{
								"activity": "CopyFile2toSQL",
								"dependencyConditions": [
									"Succeeded"
								]
							}
						],
						"policy": {
							"timeout": "0.12:00:00",
							"retry": 0,
							"retryIntervalInSeconds": 30,
							"secureOutput": false,
							"secureInput": false
						},
						"userProperties": [],
						"typeProperties": {
							"source": {
								"type": "DelimitedTextSource",
								"storeSettings": {
									"type": "AzureBlobStorageReadSettings",
									"recursive": true,
									"enablePartitionDiscovery": false
								},
								"formatSettings": {
									"type": "DelimitedTextReadSettings"
								}
							},
							"sink": {
								"type": "AzureSqlSink",
								"writeBehavior": "insert",
								"sqlWriterUseTableLock": false
							},
							"enableStaging": false,
							"translator": {
								"type": "TabularTranslator",
								"mappings": [
									{
										"source": {
											"name": "Id",
											"type": "String",
											"physicalType": "String"
										},
										"sink": {
											"name": "Id",
											"type": "Int32",
											"physicalType": "int"
										}
									},
									{
										"source": {
											"name": "Name",
											"type": "String",
											"physicalType": "String"
										},
										"sink": {
											"name": "Name",
											"type": "String",
											"physicalType": "varchar"
										}
									},
									{
										"source": {
											"name": "City",
											"type": "String",
											"physicalType": "String"
										},
										"sink": {
											"name": "City",
											"type": "String",
											"physicalType": "varchar"
										}
									}
								],
								"typeConversion": true,
								"typeConversionSettings": {
									"allowDataTruncation": true,
									"treatBooleanAsNumber": false
								}
							}
						},
						"inputs": [
							{
								"referenceName": "DelimitedText3",
								"type": "DatasetReference",
								"parameters": {}
							}
						],
						"outputs": [
							{
								"referenceName": "AzureSqlTable1",
								"type": "DatasetReference",
								"parameters": {}
							}
						]
					},
					{
						"name": "Lookup1",
						"description": "Truncate table ",
						"type": "Lookup",
						"dependsOn": [],
						"policy": {
							"timeout": "0.12:00:00",
							"retry": 0,
							"retryIntervalInSeconds": 30,
							"secureOutput": false,
							"secureInput": false
						},
						"userProperties": [],
						"typeProperties": {
							"source": {
								"type": "AzureSqlSource",
								"sqlReaderQuery": "select * from [dbo].[CopyDemo];",
								"queryTimeout": "02:00:00",
								"partitionOption": "None"
							},
							"dataset": {
								"referenceName": "AzureSqlTable1",
								"type": "DatasetReference",
								"parameters": {}
							},
							"firstRowOnly": false
						}
					}
				],
				"policy": {
					"elapsedTimeMetric": {}
				},
				"annotations": []
			},
			"dependsOn": [
				"[concat(variables('factoryId'), '/datasets/DelimitedText1')]",
				"[concat(variables('factoryId'), '/datasets/AzureSqlTable1')]",
				"[concat(variables('factoryId'), '/datasets/DelimitedText2')]",
				"[concat(variables('factoryId'), '/datasets/DelimitedText3')]"
			]
		},
		{
			"name": "[concat(parameters('factoryName'), '/AzureSqlTable1')]",
			"type": "Microsoft.DataFactory/factories/datasets",
			"apiVersion": "2018-06-01",
			"properties": {
				"linkedServiceName": {
					"referenceName": "LinkedServiceAzureSQLDatabase",
					"type": "LinkedServiceReference"
				},
				"annotations": [],
				"type": "AzureSqlTable",
				"schema": [
					{
						"name": "Id",
						"type": "int",
						"precision": 10
					},
					{
						"name": "Name",
						"type": "varchar"
					},
					{
						"name": "City",
						"type": "varchar"
					}
				],
				"typeProperties": {
					"schema": "dbo",
					"table": "CopyDemo"
				}
			},
			"dependsOn": [
				"[concat(variables('factoryId'), '/linkedServices/LinkedServiceAzureSQLDatabase')]"
			]
		},
		{
			"name": "[concat(parameters('factoryName'), '/DelimitedText1')]",
			"type": "Microsoft.DataFactory/factories/datasets",
			"apiVersion": "2018-06-01",
			"properties": {
				"linkedServiceName": {
					"referenceName": "AzureBlobStorage1",
					"type": "LinkedServiceReference"
				},
				"annotations": [],
				"type": "DelimitedText",
				"typeProperties": {
					"location": {
						"type": "AzureBlobStorageLocation",
						"fileName": "file1.txt",
						"container": "sharedfolder"
					},
					"columnDelimiter": ",",
					"escapeChar": "\\",
					"firstRowAsHeader": true,
					"quoteChar": "\""
				},
				"schema": [
					{
						"name": "Id",
						"type": "String"
					},
					{
						"name": "Name",
						"type": "String"
					},
					{
						"name": "City",
						"type": "String"
					}
				]
			},
			"dependsOn": [
				"[concat(variables('factoryId'), '/linkedServices/AzureBlobStorage1')]"
			]
		},
		{
			"name": "[concat(parameters('factoryName'), '/DelimitedText2')]",
			"type": "Microsoft.DataFactory/factories/datasets",
			"apiVersion": "2018-06-01",
			"properties": {
				"linkedServiceName": {
					"referenceName": "AzureBlobStorage1",
					"type": "LinkedServiceReference"
				},
				"annotations": [],
				"type": "DelimitedText",
				"typeProperties": {
					"location": {
						"type": "AzureBlobStorageLocation",
						"fileName": "file2.txt",
						"container": "sharedfolder"
					},
					"columnDelimiter": ",",
					"escapeChar": "\\",
					"firstRowAsHeader": true,
					"quoteChar": "\""
				},
				"schema": [
					{
						"name": "Id",
						"type": "String"
					},
					{
						"name": "Name",
						"type": "String"
					},
					{
						"name": "City",
						"type": "String"
					}
				]
			},
			"dependsOn": [
				"[concat(variables('factoryId'), '/linkedServices/AzureBlobStorage1')]"
			]
		},
		{
			"name": "[concat(parameters('factoryName'), '/DelimitedText3')]",
			"type": "Microsoft.DataFactory/factories/datasets",
			"apiVersion": "2018-06-01",
			"properties": {
				"linkedServiceName": {
					"referenceName": "AzureBlobStorage1",
					"type": "LinkedServiceReference"
				},
				"annotations": [],
				"type": "DelimitedText",
				"typeProperties": {
					"location": {
						"type": "AzureBlobStorageLocation",
						"fileName": "file3.txt",
						"container": "sharedfolder"
					},
					"columnDelimiter": ",",
					"escapeChar": "\\",
					"firstRowAsHeader": true,
					"quoteChar": "\""
				},
				"schema": [
					{
						"name": "Id",
						"type": "String"
					},
					{
						"name": "Name",
						"type": "String"
					},
					{
						"name": "City",
						"type": "String"
					}
				]
			},
			"dependsOn": [
				"[concat(variables('factoryId'), '/linkedServices/AzureBlobStorage1')]"
			]
		},
		{
			"name": "[concat(parameters('factoryName'), '/AzureBlobStorage1')]",
			"type": "Microsoft.DataFactory/factories/linkedServices",
			"apiVersion": "2018-06-01",
			"properties": {
				"annotations": [],
				"type": "AzureBlobStorage",
				"typeProperties": {
					"connectionString": "[parameters('AzureBlobStorage1_connectionString')]"
				}
			},
			"dependsOn": []
		},
		{
			"name": "[concat(parameters('factoryName'), '/LinkedServiceAzureSQLDatabase')]",
			"type": "Microsoft.DataFactory/factories/linkedServices",
			"apiVersion": "2018-06-01",
			"properties": {
				"annotations": [],
				"type": "AzureSqlDatabase",
				"typeProperties": {
					"server": "[parameters('LinkedServiceAzureSQLDatabase_properties_typeProperties_server')]",
					"database": "[parameters('LinkedServiceAzureSQLDatabase_properties_typeProperties_database')]",
					"encrypt": "mandatory",
					"trustServerCertificate": false,
					"authenticationType": "SQL",
					"userName": "[parameters('LinkedServiceAzureSQLDatabase_properties_typeProperties_userName')]",
					"password": {
						"type": "SecureString",
						"value": "[parameters('LinkedServiceAzureSQLDatabase_password')]"
					}
				}
			},
			"dependsOn": []
		},
		{
			"name": "[concat(parameters('factoryName'), '/linkedServiceSelfhost')]",
			"type": "Microsoft.DataFactory/factories/linkedServices",
			"apiVersion": "2018-06-01",
			"properties": {
				"annotations": [],
				"type": "FileServer",
				"typeProperties": {
					"host": "[parameters('linkedServiceSelfhost_properties_typeProperties_host')]",
					"userId": "[parameters('linkedServiceSelfhost_properties_typeProperties_userId')]",
					"password": {
						"type": "SecureString",
						"value": "[parameters('linkedServiceSelfhost_password')]"
					}
				},
				"connectVia": {
					"referenceName": "SelfHostedLaptopIR",
					"type": "IntegrationRuntimeReference"
				}
			},
			"dependsOn": [
				"[concat(variables('factoryId'), '/integrationRuntimes/SelfHostedLaptopIR')]"
			]
		},
		{
			"name": "[concat(parameters('factoryName'), '/SelfHostedLaptopIR')]",
			"type": "Microsoft.DataFactory/factories/integrationRuntimes",
			"apiVersion": "2018-06-01",
			"properties": {
				"type": "SelfHosted",
				"typeProperties": {}
			},
			"dependsOn": []
		}
	]
}